tml_ctp/__init__.py
tml_ctp/info.py
tml_ctp/cli/__init__.py
tml_ctp/cli/ctp_dat_batcher.py
tml_ctp/cli/utils/__init__.py
tml_ctp/cli/utils/clean_series_tags.py
tml_ctp/cli/utils/delete_identifiable_dicoms.py
tml_ctp-1.1.1.dist-info/LICENSE
tml_ctp-1.1.1.dist-info/METADATA
tml_ctp-1.1.1.dist-info/WHEEL
tml_ctp-1.1.1.dist-info/entry_points.txt
tml_ctp-1.1.1.dist-info/top_level.txt
tml_ctp-1.1.1.dist-info/RECORD
