Metadata-Version: 2.1
Name: tml_ctp
Version: 1.1.1
Summary: Python tool to batch anonymization of DICOM files with Dockerized CTP Dicom Anonymizer Tool
Home-page: https://github.com/TranslationalML/tml-ctp
Author: The TranslationalML Team
Author-email: translationalML@gmail.com
License: Mozilla Public License Version 2.0
Project-URL: Documentation, https://github.com/TranslationalML/tml-ctp  # TODO: update with ReadTheDocs link when sphinx documentation is set up
Classifier: Development Status :: 5 - Production/Stable
Classifier: Intended Audience :: Science/Research
Classifier: Topic :: Scientific/Engineering
Classifier: License :: OSI Approved :: Mozilla Public License 2.0 (MPL 2.0)
Classifier: Programming Language :: Python :: 3.10
Requires-Python: >=3.10
License-File: LICENSE
Requires-Dist: pydicom==2.4
Requires-Dist: tqdm==4.66
Requires-Dist: pandas==2.2
Requires-Dist: numpy==1.26
Provides-Extra: all
Requires-Dist: pydot==2.0; extra == "all"
Requires-Dist: sphinx==7.2; extra == "all"
Requires-Dist: sphinx-argparse==0.4; extra == "all"
Requires-Dist: sphinx-rtd-theme==2.0; extra == "all"
Requires-Dist: recommonmark==0.7; extra == "all"
Requires-Dist: sphinxcontrib-apidoc==0.5; extra == "all"
Requires-Dist: sphinxcontrib-mermaid==0.9; extra == "all"
Requires-Dist: sphinxemoji==0.3; extra == "all"
Requires-Dist: mock==5.1; extra == "all"
Requires-Dist: myst-parser==4.0; extra == "all"
Requires-Dist: docutils==0.20; extra == "all"
Requires-Dist: commonmark==0.9; extra == "all"
Requires-Dist: black==24.2; extra == "all"
Requires-Dist: pre-commit==3.6; extra == "all"
Requires-Dist: isort==5.13; extra == "all"
Requires-Dist: pytest==7.4; extra == "all"
Requires-Dist: pytest-console-scripts==1.4; extra == "all"
Requires-Dist: pytest-cov==4.1; extra == "all"
Requires-Dist: pytest-order==1.2; extra == "all"
Provides-Extra: dev
Requires-Dist: black==24.2; extra == "dev"
Requires-Dist: pre-commit==3.6; extra == "dev"
Requires-Dist: isort==5.13; extra == "dev"
Provides-Extra: doc
Requires-Dist: pydot==2.0; extra == "doc"
Requires-Dist: sphinx==7.2; extra == "doc"
Requires-Dist: sphinx-argparse==0.4; extra == "doc"
Requires-Dist: sphinx-rtd-theme==2.0; extra == "doc"
Requires-Dist: recommonmark==0.7; extra == "doc"
Requires-Dist: sphinxcontrib-apidoc==0.5; extra == "doc"
Requires-Dist: sphinxcontrib-mermaid==0.9; extra == "doc"
Requires-Dist: sphinxemoji==0.3; extra == "doc"
Requires-Dist: mock==5.1; extra == "doc"
Requires-Dist: myst-parser==4.0; extra == "doc"
Requires-Dist: docutils==0.20; extra == "doc"
Requires-Dist: commonmark==0.9; extra == "doc"
Provides-Extra: docs
Requires-Dist: pydot==2.0; extra == "docs"
Requires-Dist: sphinx==7.2; extra == "docs"
Requires-Dist: sphinx-argparse==0.4; extra == "docs"
Requires-Dist: sphinx-rtd-theme==2.0; extra == "docs"
Requires-Dist: recommonmark==0.7; extra == "docs"
Requires-Dist: sphinxcontrib-apidoc==0.5; extra == "docs"
Requires-Dist: sphinxcontrib-mermaid==0.9; extra == "docs"
Requires-Dist: sphinxemoji==0.3; extra == "docs"
Requires-Dist: mock==5.1; extra == "docs"
Requires-Dist: myst-parser==4.0; extra == "docs"
Requires-Dist: docutils==0.20; extra == "docs"
Requires-Dist: commonmark==0.9; extra == "docs"
Provides-Extra: test
Requires-Dist: pytest==7.4; extra == "test"
Requires-Dist: pytest-console-scripts==1.4; extra == "test"
Requires-Dist: pytest-cov==4.1; extra == "test"
Requires-Dist: pytest-order==1.2; extra == "test"
